pytensors/__init__.py
pytensors/__main__.py
pytensors/libs/__init__.py
pytensors-0.10.0.dist-info/METADATA
pytensors-0.10.0.dist-info/WHEEL
pytensors-0.10.0.dist-info/top_level.txt
pytensors-0.10.0.dist-info/RECORD
