Metadata-Version: 2.1
Name: pytensors
Version: 0.10.0
Summary: Interact with Python Tensors
Home-page: https://github.com/tensorframe/pytensors
Author: Anthony Potappel
Author-email: anthony.potappel@gmail.com
License: UNKNOWN
Platform: UNKNOWN
Classifier: Operating System :: POSIX :: Linux
Classifier: License :: OSI Approved :: MIT License
Classifier: Programming Language :: Python :: 3.5
Classifier: Programming Language :: Python :: 3.6
Classifier: Programming Language :: Python :: 3.7
